scdbf/__init__.py
scdbf/scdbf.py
scdbf-0.0.4.dist-info/LICENSE
scdbf-0.0.4.dist-info/METADATA
scdbf-0.0.4.dist-info/WHEEL
scdbf-0.0.4.dist-info/entry_points.txt
scdbf-0.0.4.dist-info/top_level.txt
scdbf-0.0.4.dist-info/RECORD
