Metadata-Version: 2.1
Name: scdbf
Version: 0.0.4
Summary: Simple cat for dbf files
Author-email: Jesus Baizabal <baizabal.jesus@gmail.com>
License: MIT
Project-URL: Homepage, https://github.com/ambagasdowa/scdbf
Project-URL: Bug Tracker, https://github.com/ambagasdowa/scdbf/issues
Keywords: cat,dbf
Classifier: Programming Language :: Python :: 3
Classifier: License :: OSI Approved :: MIT License
Classifier: Operating System :: OS Independent
Requires-Python: >=3.5
License-File: LICENSE
Requires-Dist: dbfread
